src/consolechars/consolechars.py
consolechars-0.0.3.dist-info/METADATA
consolechars-0.0.3.dist-info/WHEEL
consolechars-0.0.3.dist-info/licenses/LICENSE
consolechars-0.0.3.dist-info/RECORD
