Metadata-Version: 2.1
Name: consolechars
Version: 0.0.3
Summary: Alphabet for Python
Project-URL: Homepage, https://google.com/404/
Project-URL: Bug Tracker, https://google.com/404/
Author-email: AcronimZ <matvey.dibrov123@gmail.com>
License: Copyright (c) 2018 The Python Packaging Authority
Classifier: License :: OSI Approved :: MIT License
Classifier: Operating System :: OS Independent
Classifier: Programming Language :: Python :: 3
Requires-Python: >=3.7
